{
    "title": "Data Cellar Participant Template",
    "creators": [
        {
            "name": "Azzabi, Radhouene",
            "affiliation": "CEA"
        },
        {
            "name": "Vassiliadis, Michalis",
            "affiliation": "QUE Technologies"
        },
        {
            "name": "Garcia Mangas, Andres",
            "affiliation": "CTIC",
            "orcid": "0000-0002-8010-8681"
        }
    ],
    "keywords": [
        "data space",
        "eclipse dataspace components",
        "verifiable credentials",
        "data cellar",
        "horizon europe",
        "edc connector",
        "federated data exchange"
    ],
    "communities": [
        {
            "identifier": "datacellar"
        }
    ]
}